metripy/__init__.py
metripy/metripy.py
metripy/Application/Analyzer.py
metripy/Application/Application.py
metripy/Application/Info.py
metripy/Application/__init__.py
metripy/Application/Config/CodeSmellConfig.py
metripy/Application/Config/Config.py
metripy/Application/Config/GitConfig.py
metripy/Application/Config/Parser.py
metripy/Application/Config/ProjectConfig.py
metripy/Application/Config/ReportConfig.py
metripy/Application/Config/File/ConfigFileReaderFactory.py
metripy/Application/Config/File/ConfigFileReaderInterface.py
metripy/Application/Config/File/JsonConfigFileReader.py
metripy/Application/Config/File/PathResolver.py
metripy/Application/Config/File/YamlConfigFileReader.py
metripy/Component/Debug/Debugger.py
metripy/Component/File/Finder.py
metripy/Component/Output/CliOutput.py
metripy/Component/Output/ProgressBar.py
metripy/DebugUtils/AstDumper.py
metripy/Dependency/Dependency.py
metripy/Dependency/Composer/Composer.py
metripy/Dependency/Composer/Packegist.py
metripy/Dependency/Npm/Npm.py
metripy/Dependency/Npm/NpmOrg.py
metripy/Dependency/Pip/Pip.py
metripy/Dependency/Pip/PyPi.py
metripy/Git/GitAnalyzer.py
metripy/Import/Json/JsonImporter.py
metripy/LangAnalyzer/AbstractLangAnalyzer.py
metripy/LangAnalyzer/__init__.py
metripy/LangAnalyzer/Generic/__init__.py
metripy/LangAnalyzer/Generic/Ast/AstParser.py
metripy/LangAnalyzer/Generic/CodeSmell/CodeSmell.py
metripy/LangAnalyzer/Generic/CodeSmell/CodeSmellDetectorFactory.py
metripy/LangAnalyzer/Generic/CodeSmell/GenericCodeSmellDetector.py
metripy/LangAnalyzer/Generic/CodeSmell/__init__.py
metripy/LangAnalyzer/Generic/CodeSmell/Detectors/BaseDetector.py
metripy/LangAnalyzer/Generic/CodeSmell/Detectors/NamingConventionDetector.py
metripy/LangAnalyzer/Generic/CodeSmell/Detectors/TooManyParametersDetector.py
metripy/LangAnalyzer/Generic/CodeSmell/Detectors/UnusedFunctionsDetector.py
metripy/LangAnalyzer/Generic/CodeSmell/Detectors/UnusedImportsDetector.py
metripy-0.7.3.dist-info/licenses/LICENSE
metripy-0.7.3.dist-info/METADATA
metripy-0.7.3.dist-info/WHEEL
metripy-0.7.3.dist-info/entry_points.txt
metripy-0.7.3.dist-info/top_level.txt
metripy-0.7.3.dist-info/RECORD
