Metadata-Version: 2.4
Name: metripy
Version: 0.7.3
Summary: A Python tool to generate multi project, multi language code metric reports
Author-email: Yannick Zimmermann <yannick.zimmermann@proton.me>
License: MIT
Project-URL: Homepage, https://zimmer-yan.github.io/metripy/
Project-URL: Repository, https://github.com/zimmer-yan/metripy
Project-URL: Documentation, https://zimmer-yan.github.io/metripy/
Project-URL: Bug Tracker, https://github.com/zimmer-yan/metripy/issues
Keywords: code metrics,multi-language,code analysis,git metrics,code visualization,software quality,static analysis,repository insights,developer productivity,codebase health,technical debt,language-agnostic
Classifier: Development Status :: 3 - Alpha
Classifier: Intended Audience :: Developers
Classifier: Programming Language :: Python :: 3
Classifier: Programming Language :: Python :: 3.11
Classifier: Programming Language :: Python :: 3.12
Requires-Python: >=3.11
License-File: LICENSE
Requires-Dist: lizard==1.18.0
Requires-Dist: GitPython==3.1.45
Requires-Dist: py-template-engine>=0.2.6
Requires-Dist: radon==6.0.1
Requires-Dist: requests==2.32.5
Requires-Dist: packaging==25.0
Requires-Dist: toml==0.10.2
Requires-Dist: tree-sitter==0.21.3
Requires-Dist: tree-sitter-languages==1.10.2
Requires-Dist: PyYAML==6.0.3
Requires-Dist: simhash==2.1.2
Requires-Dist: term-piechart==0.1.3
Provides-Extra: dev
Requires-Dist: pytest>=7.0.0; extra == "dev"
Requires-Dist: pytest-cov==7.0.0; extra == "dev"
Requires-Dist: pytest-mock==3.15.1; extra == "dev"
Requires-Dist: black>=22.0.0; extra == "dev"
Requires-Dist: flake8>=5.0.0; extra == "dev"
Requires-Dist: mypy>=0.991; extra == "dev"
Requires-Dist: poethepoet==0.37.0; extra == "dev"
Requires-Dist: isort==7.0.0; extra == "dev"
Dynamic: license-file
